<?xml version="1.0" encoding="UTF-8"?>
<!--

    Copyright (C) 2003-2011 eXo Platform SAS.

    This program is free software; you can redistribute it and/or
    modify it under the terms of the GNU Affero General Public License
    as published by the Free Software Foundation; either version 3
    of the License, or (at your option) any later version.

    This program is distributed in the hope that it will be useful,
    but WITHOUT ANY WARRANTY; without even the implied warranty of
    MERCHANTABILITY or FITNESS FOR A PARTICULAR PURPOSE.  See the
    GNU General Public License for more details.

    You should have received a copy of the GNU General Public License
    along with this program; if not, see<http://www.gnu.org/licenses/>.

-->
<Module>
  <ModulePrefs  title="Stream Mixer"
                description="Stream Mixer: eXo Platform, Twitter, Facebook, LinkedIn..."
                author="Hoat Le, Ly Minh Phuong"
                author_email="hoatlevan@gmail.com"
                author_affiliation="eXo Platform">
    <Locale messages="locale/ALL_ALL.xml" />
    <Locale lang="en" messages="locale/en_ALL.xml" />
    <Locale lang="fr" messages="locale/fr_ALL.xml" />
    <Locale lang="vi" messages="locale/vi_ALL.xml" />
    <Require feature="opensocial-0.8" />
    <Require feature="dynamic-height" />
    <Require feature="settitle" />  
    <Require feature="views" />
    <Require feature="minimessage" />
  </ModulePrefs>
  <Content type="html" view="default, home, profile, canvas">
  <![CDATA[
    <link rel="stylesheet" type="text/css" href="style/jquery-ui-1.8.12.custom.css" />
    <link rel="stylesheet" type="text/css" href="style/style.css" />
    <script type="text/javascript" src="script/debug.js"></script>
    <!-- Dev Mode -->
    <!--
    <script type="text/javascript" src="script/jquery-1.6.1.js"></script>
    <script type="text/javascript" src="script/jquery-ui-1.18.12.js"></script>
    <script type="text/javascript" src="script/Configuration.js"></script>
    <script type="text/javascript" src="script/Locale.js"></script>
    <script type="text/javascript" src="script/Util.js"></script>
    <script type="text/javascript" src="script/AccountManager.js"></script>
    <script type="text/javascript" src="script/Activity.js"></script>
    <script type="text/javascript" src="script/ActivityComposer.js"></script>
    <script type="text/javascript" src="script/ActivityStream.js"></script>
    <script type="text/javascript" src="script/StreamMixer.js"></script>
    -->
    <!-- Prod Mode -->
    <script type="text/javascript" src="script/jquery-1.16.1.min.js"></script>
    <script type="text/javascript" src="script/jquery-ui-1.18.12.min.js"></script>
    <script type="text/javascript" src="script/merged.min.js"></script>
    <div id="StreamMixer">
      <div id="progressbar"></div>

      <div id="Activitytemplate" class="Activity" style="display:none;">
        <img id="avatarIcon" class="avatarIcon"/>
        <div id="header">
          <img id="activityIcon" class="activityIcon"/>
          <span id="displayName" class="displayName"></span>
          (<span id="postedDay" class="postedDay"></span>)
        </div>
        <div id="content" class="content"></div>
      </div>

      <div id="LoginForm" class="LoginForm" style="display: none;">
        <img id="socialLogo" class="socialNetworkLogo"/>
        <br/>
        <label for="userName">_MSG_username__:</label><input id="userName"></input>
        <br/>
        <label for="passWord">_MSG_password__:</label><input id="passWord"></input>
        <br/>
        <label>&nbsp;</label>
        <input type="button" value="_MSG_login__"></input>
      </div>
      <br/>

      <div id="ActivityContent" style="display: none;">
        <div id="Activities">

        </div>
      </div>
    </div>
  ]]>
  </Content>
</Module>
